<?xml version='1.0' encoding='utf-8'?>
<recording_script>
  <fileid id="z0001_000">смеху теперь будет на весь петербург</fileid>
  <fileid id="z0001_001">так кажется на первый взгляд</fileid>
  <fileid id="z0001_002">рубенс не музыкант а художник</fileid>
  <fileid id="z0001_003">штирнер и фит ушли вперед</fileid>
  <fileid id="z0001_004">сняв колпак и отдышавшись зурита спросил</fileid>
  <fileid id="z0001_005">демьян лукич убирал желудочный зонд</fileid>
  <fileid id="z0001_006">я еще не пустил в ход всех моих средств</fileid>
  <fileid id="z0001_007">где уж тут хлеб ваша милость</fileid>
  <fileid id="z0001_008">а теперь ты не боишься</fileid>
  <fileid id="z0001_009">марусю то ведь кто нибудь должен нянчить</fileid>
  <fileid id="z0001_010">асокин узнавал себя во всем</fileid>
  <fileid id="z0001_011">ус был мокрый как от дождя</fileid>
  <fileid id="z0001_012">дугов стал смотреть на птиц</fileid>
  <fileid id="z0001_013">в руках он держал пиджак</fileid>
  <fileid id="z0001_014">бендер выдал мальчику честно заработанный рубль</fileid>
  <fileid id="z0001_015">уважайте пружинный матрац в голубых цветочках</fileid>
  <fileid id="z0001_016">он хитро подмигнул светя улыбке огнем трубки</fileid>
  <fileid id="z0001_017">он держит в своих пальцах жизнь и смерть</fileid>
  <fileid id="z0001_018">а у нас нет почек</fileid>
  <fileid id="z0001_019">наш хозяин сам родом из римлян</fileid>
  <fileid id="z0001_020">пусть льется кровь сильных в защиту слабых</fileid>
  <fileid id="z0001_021">надпись эту остап прочел вслух</fileid>
  <fileid id="z0001_022">поезд опять нырнул в туннель</fileid>
  <fileid id="z0001_023">а у юбиляра нет почек</fileid>
  <fileid id="z0001_024">подымется визг оханье и плач</fileid>
  <fileid id="z0001_025">сяду и даже чашечку чаю выпью</fileid>
  <fileid id="z0001_026">в ужасе вскрикнула и эльза</fileid>
  <fileid id="z0001_027">к ним рысью приближалась барышня</fileid>
  <fileid id="z0001_028">причинив мне боль исчезает без следа</fileid>
  <fileid id="z0001_029">никола исчез в снежном сугробе</fileid>
  <fileid id="z0001_030">члены общества и их прозвища</fileid>
  <fileid id="z0001_031">срок для обжалования близился к концу</fileid>
  <fileid id="z0001_032">а участь попавших в мой музей прекрасна</fileid>
  <fileid id="z0001_033">неудавшаяся кража в театре колумба</fileid>
  <fileid id="z0001_034">а ты сам сразу не можешь разобрать</fileid>
  <fileid id="z0001_035">эмма побледнела от горя и обиды</fileid>
  <fileid id="z0001_036">ты еще веришь в ноздрю</fileid>
  <fileid id="z0001_037">и он взялся за кирку</fileid>
  <fileid id="z0001_038">а я думала тумба для афиш</fileid>
  <fileid id="z0001_039">мы и соль у кухарки украдем</fileid>
  <fileid id="z0001_040">извозчик издал губами поцелуйный звук</fileid>
  <fileid id="z0001_041">и в виде заключительного аккорда</fileid>
  <fileid id="z0001_042">мы жили бы под землей и уничтожили бы время</fileid>
  <fileid id="z0001_043">хоть бы он был жив</fileid>
  <fileid id="z0001_044">сорви ж былиночку и вспомни обо мне</fileid>
  <fileid id="z0001_045">да ведь мы по рюмочке</fileid>
  <fileid id="z0001_046">и в мыслях не имел</fileid>
  <fileid id="z0001_047">тогда он понял что ошибся</fileid>
  <fileid id="z0001_048">возьму вот и повешусь на дверях</fileid>
  <fileid id="z0001_049">купальня ведь в двух шагах</fileid>
  <fileid id="z0001_050">скрадет у тетки деньги вот и все</fileid>
  <fileid id="z0001_051">сальватор начал прощупывать пальцами опухоль на горле ребенка</fileid>
  <fileid id="z0001_052">солнце каталось в ситечке как яйцо</fileid>
  <fileid id="z0001_053">я дам тебе теплую одежду револьвер и мешок с сухарями и вяленым мясом</fileid>
  <fileid id="z0001_054">среднее между рыбой и мясом</fileid>
  <fileid id="z0001_055">отец федор не стал медлить</fileid>
  <fileid id="z0001_056">для публики это канальски эффектно</fileid>
  <fileid id="z0001_057">часы эти впоследствии купил сын фельдмаршала графа каменского</fileid>
  <fileid id="z0001_058">на лысой горе произошел взрыв</fileid>
  <fileid id="z0001_059">светящийся гигант понес компаньонов вниз по реке</fileid>
  <fileid id="z0001_060">утро другого дня застало эллочку в парикмахерской</fileid>
  <fileid id="z0001_061">я слышу сквозь шум крови опять скрипит дверь</fileid>
  <fileid id="z0001_062">во что я обращусь завтра</fileid>
  <fileid id="z0001_063">на другой день савицкий был исключен из гимназии</fileid>
  <fileid id="z0001_064">толки о нем в москве</fileid>
  <fileid id="z0001_065">официант стал топтаться как конь</fileid>
  <fileid id="z0001_066">а когда же наша свадьба</fileid>
  <fileid id="z0001_067">там темно как в брюхе акулы</fileid>
  <fileid id="z0001_068">он сообщал о ряде неудач</fileid>
  <fileid id="z0001_069">зверь сам должен бежать на ловца</fileid>
  <fileid id="z0001_070">в корзине из под белья</fileid>
  <fileid id="z0001_071">папа щукин взял ссуду в кассе взаимопомощи</fileid>
  <fileid id="z0001_072">в руке он держал брюки</fileid>
  <fileid id="z0001_073">в тюрьме сидит за растрату</fileid>
  <fileid id="z0001_074">сеанс одновременной игры в шахмат</fileid>
  <fileid id="z0001_075">он был хитер как кошка пампасов</fileid>
  <fileid id="z0001_076">лицо людвига вдруг стало жестким</fileid>
  <fileid id="z0001_077">почему бы мне быть желтым</fileid>
  <fileid id="z0001_078">в тысячу в миллион раз легче</fileid>
  <fileid id="z0001_079">но вот не семен а иван карпов</fileid>
  <fileid id="z0001_080">так и вперлись ахнул турбин</fileid>
  <fileid id="z0001_081">не слишком ли это будет бить на дешевый эффект</fileid>
  <fileid id="z0001_082">на лице штирнера отражались счастье и печаль</fileid>
  <fileid id="z0001_083">ведь ты их целый месяц есть будешь</fileid>
  <fileid id="z0001_084">ведь ты разбойник тебя и надо в тюрьму</fileid>
  <fileid id="z0001_085">кузя толкнул мецената локтем в бок</fileid>
  <fileid id="z0001_086">теперь вы к нам семен мироныч</fileid>
  <fileid id="z0001_087">ну а с иваном что</fileid>
  <fileid id="z0001_088">у эммы отлегло от сердца</fileid>
  <fileid id="z0001_089">а мазь давал леонтий леонтьевич</fileid>
  <fileid id="z0001_090">они также улеглись у ног дугова</fileid>
  <fileid id="z0001_091">хиромант принял нас очень любезно</fileid>
  <fileid id="z0001_092">трудно понять китайцев и женщин</fileid>
  <fileid id="z0001_093">вся москва покатывается со смеху</fileid>
  <fileid id="z0001_094">часа в три в четыре</fileid>
  <fileid id="z0001_095">какой смысл раз все уже счастливы</fileid>
  <fileid id="z0001_096">почему же он в форме гребенки</fileid>
  <fileid id="z0001_097">сразу все взвихрилось поднялось со дна</fileid>
  <fileid id="z0001_098">а почему вы в шляпе</fileid>
  <fileid id="z0001_099">я не могу уйти без кольца</fileid>
  <fileid id="z0001_100">когда я уйду здесь все пойдет вверх дном</fileid>
  <fileid id="z0001_101">медведь бьет и человек бьет формулировал никола свой фатализм</fileid>
  <fileid id="z0001_102">это был человек созвучный эпохе</fileid>
  <fileid id="z0001_103">вот ты уже и улыбаешься</fileid>
  <fileid id="z0001_104">ведь ведет же дорога к жилью</fileid>
  <fileid id="z0001_105">дай то бог всхлипнула жена</fileid>
  <fileid id="z0001_106">пошел мелкий снег и вдруг повалил хлопьями</fileid>
  <fileid id="z0001_107">где то недалеко пели туземцы</fileid>
  <fileid id="z0001_108">да ведь как его отвезешь то</fileid>
  <fileid id="z0001_109">счастлив ли ты так же как я</fileid>
  <fileid id="z0001_110">а ведь вы не были в бюро хранителей</fileid>
  <fileid id="z0001_111">а отчего мотька спать хочет</fileid>
  <fileid id="z0001_112">обхаянному на лекции брюнету он пожертвовал даже ферзя</fileid>
  <fileid id="z0001_113">где же он может быть</fileid>
  <fileid id="z0001_114">вы вступили на очень скользкий путь</fileid>
  <fileid id="z0001_115">церковь при доме графа шереметева</fileid>
  <fileid id="z0001_116">да он и есть ребенок</fileid>
  <fileid id="z0001_117">нужны деньги на хлеб и любительскую колбасу</fileid>
  <fileid id="z0001_118">внезапно остап заревел и схватил воробьянинова за бицепс</fileid>
  <fileid id="z0001_119">он был холоден и готов к борьбе</fileid>
  <fileid id="z0001_120">треухов фыркал и шел в кухню пилить дрова</fileid>
  <fileid id="z0001_121">через минуту он явился с длинной палкой</fileid>
  <fileid id="z0001_122">а я боюсь только пьяных</fileid>
  <fileid id="z0001_123">до свиданья а не прощайте</fileid>
  <fileid id="z0001_124">это не англичане а французы</fileid>
  <fileid id="z0001_125">я не только сведущ в финансах но и перевернут</fileid>
  <fileid id="z0001_126">отчего же вы не пьете ваш херес</fileid>
  <fileid id="z0001_127">наш путь лежал к отрогу верхоянского хребта</fileid>
  <fileid id="z0001_128">у меня глаз как у орла</fileid>
  <fileid id="z0001_129">вы уж его не обижайте</fileid>
  <fileid id="z0001_130">тальберга берут у тальберга нашлись связи</fileid>
  <fileid id="z0001_131">из всех четырех лучший характер у меня</fileid>
  <fileid id="z0001_132">тысяча семьсот девяносто семь в лист</fileid>
  <fileid id="z0001_133">вообще в большом городе жизнь хлопотливая вещь</fileid>
  <fileid id="z0001_134">крысаков очень дружен с сандерсом</fileid>
  <fileid id="z0001_135">вы всю ночь мне грезились</fileid>
  <fileid id="z0001_136">а ну ка сыграй съемки</fileid>
  <fileid id="z0001_137">легкий шорох и передо мною двоякоизогнутая тень</fileid>
  <fileid id="z0001_138">и как он мог идти</fileid>
  <fileid id="z0001_139">ламы брали хлеб из рук</fileid>
  <fileid id="z0001_140">но он сильнее злых духов</fileid>
  <fileid id="z0001_141">вас бы там встретили по царски</fileid>
  <fileid id="z0001_142">тут делов полно а на больницу полдня</fileid>
  <fileid id="z0001_143">и у всякого бинокль из глаз торчит</fileid>
  <fileid id="z0001_144">как беззвучное эхо отозвались сразу и фельдшер и анна николаевна</fileid>
  <fileid id="z0001_145">а у этих зубы кариозные</fileid>
  <fileid id="z0001_146">вы ведь вечно рыщете за полтинником</fileid>
  <fileid id="z0001_147">вы ведь не из трусливого десятка</fileid>
  <fileid id="z0001_148">мы это ночью все сварганим</fileid>
  <fileid id="z0001_149">толпа запруживает всю площадь перед биржей</fileid>
  <fileid id="z0001_150">если кто нибудь рвет зуб</fileid>
  <fileid id="z0001_151">у вас грудь не болит от машинки</fileid>
  <fileid id="z0001_152">я из своих им куплю</fileid>
  <fileid id="z0001_153">за конспирацию товарищ фельдмаршал быстро ответил бендер</fileid>
  <fileid id="z0001_154">а там котлеты из лапши</fileid>
  <fileid id="z0001_155">возвращаемся опять к сыну фельдмаршала каменского</fileid>
  <fileid id="z0001_156">остап долго разворачивал экземпляр станка</fileid>
  <fileid id="z0001_157">активисты летали молча с серьезными лицами</fileid>
  <fileid id="z0001_158">лишь бы опять не сбиться</fileid>
  <fileid id="z0001_159">все гибнет тихо шептала она</fileid>
  <fileid id="z0001_160">один вагончик ползет вверх другой вниз</fileid>
  <fileid id="z0001_161">на каждом из них есть цифра</fileid>
  <fileid id="z0001_162">надо ж пиджаки вешать же ж</fileid>
  <fileid id="z0001_163">ну что там ваш журнал</fileid>
  <fileid id="z0001_164">а через час уже звонил телефон</fileid>
  <fileid id="z0001_165">журнал наполнен мелкими статейками и стихотворениями</fileid>
  <fileid id="z0001_166">он хотел быть дьявольским моряком</fileid>
  <fileid id="z0001_167">так и буду летать по вьюге</fileid>
  <fileid id="z0001_168">но это первый шаг в обширную область культуры</fileid>
  <fileid id="z0001_169">неужели не может быть семьи без измены</fileid>
  <fileid id="z0001_170">зазвонивший телефон прервал мою патетическую речь</fileid>
  <fileid id="z0001_171">вы же скоро умрете вы же старенький</fileid>
  <fileid id="z0001_172">факел исчез как провалился или же потух</fileid>
  <fileid id="z0001_173">так что уж вы того</fileid>
  <fileid id="z0001_174">в одиннадцатом часу великий труд был закончен</fileid>
  <fileid id="z0001_175">в чем дело мой друг</fileid>
  <fileid id="z0001_176">вход в маскарад стоил рубль медью</fileid>
  <fileid id="z0001_177">в коридорах зажглись несветлые лампы</fileid>
  <fileid id="z0001_178">и разве сожженных христианами на кострах меньше</fileid>
  <fileid id="z0001_179">а потом я вас сейчас же выгоню</fileid>
  <fileid id="z0001_180">тебе нужно что нибудь потолще</fileid>
  <fileid id="z0001_181">а вы счастливый человек чтоб вас черти побрали</fileid>
  <fileid id="z0001_182">позвольте а где же отец федор</fileid>
  <fileid id="z0001_183">да вы бы их еще раз прочли</fileid>
  <fileid id="z0001_184">я вам сейчас что то сообщу</fileid>
  <fileid id="z0001_185">попытка взимать с граждан гривенники не удалась</fileid>
  <fileid id="z0001_186">никола посмотрел вперед и обмер от ужаса</fileid>
  <fileid id="z0001_187">каждый тоннель был снабжен лифтом</fileid>
  <fileid id="z0001_188">разговор его с этими паразитами образец логики и внушительности</fileid>
  <fileid id="z0001_189">вчера я получила от нее большое письмо</fileid>
  <fileid id="z0001_190">вот комик шаховской с плачевными стихам</fileid>
  <fileid id="z0001_191">концессионеры устроились на пристанских лавках</fileid>
  <fileid id="z0001_192">и как они это ловко</fileid>
  <fileid id="z0001_193">шереметев купил его с частью мебели</fileid>
  <fileid id="z0001_194">ноль целых и пять десятых</fileid>
  <fileid id="z0001_195">карин был несчастен в женитьбе</fileid>
  <fileid id="z0001_196">а розовую уж никак бы нельзя</fileid>
  <fileid id="z0001_197">ахнули за спиной у меня обе акушерки</fileid>
  <fileid id="z0001_198">и персицкий вместе с авдотьевым начали новый обход</fileid>
  <fileid id="z0001_199">теперь там помещается губернский архив</fileid>
  <fileid id="z0001_200">русский архив тысяча восемьсот семьдесят седьмой год</fileid>
  <fileid id="z0001_201">это уж как ты хочешь</fileid>
  <fileid id="z0001_202">но ведь носили же вуаль женщины</fileid>
  <fileid id="z0001_203">эй алексей григорьевич кем это ты навьючил экипаж</fileid>
  <fileid id="z0001_204">александр львович и семен кириллович нарышкины</fileid>
  <fileid id="z0001_205">и погибнет право погибнет семен</fileid>
  <fileid id="z0001_206">а теперь нам с тобой надо отдохнуть</fileid>
  <fileid id="z0001_207">ты уж меня не виновать</fileid>
  <fileid id="z0001_208">а о чем же иначе</fileid>
  <fileid id="z0001_209">князья в ладоши ей не бьют</fileid>
  <fileid id="z0001_210">а дядя мой предобрый был</fileid>
  <fileid id="z0001_211">эти сборища не обходились без непорядков</fileid>
  <fileid id="z0001_212">вы тот же великодушный рыцарь</fileid>
  <fileid id="z0001_213">ни чувства формы ни понятия о ракурсе</fileid>
  <fileid id="z0001_214">моя душа звенела как эолова арфа</fileid>
  <fileid id="z0001_215">среди работающих бегал товарищ в инженерской фуражке</fileid>
  <fileid id="z0001_216">а ты знаешь за кем я стрядаю</fileid>
  <fileid id="z0001_217">внезапный отъезд по вызову из центра</fileid>
  <fileid id="z0001_218">великий испуг поразил сердце отца федора</fileid>
  <fileid id="z0001_219">вы слыхали о гусаре схимнике</fileid>
  <fileid id="z0001_220">за ним шел технический директор брильянтовой концессии</fileid>
  <fileid id="z0001_221">но зрачки были как зрачки</fileid>
  <fileid id="z0001_222">весь город был другого цвета</fileid>
  <fileid id="z0001_223">нынче ведь четверг возразил он</fileid>
  <fileid id="z0001_224">под мягкий звон часов бур</fileid>
  <fileid id="z0001_225">наш земной шар еще очень молод</fileid>
  <fileid id="z0001_226">там были фотографии разных мужчин</fileid>
  <fileid id="z0001_227">под конец своей жизни граф</fileid>
  <fileid id="z0001_228">купил дивный серый в яблоках костюм</fileid>
  <fileid id="z0001_229">ха ха горько засмеялся он</fileid>
  <fileid id="z0001_230">водовороты завертели шлюпку льдины мешали грести</fileid>
  <fileid id="z0001_231">обед из пяти блюд с кофе рубль</fileid>
  <fileid id="z0001_232">спешно он дал мыслеприказ всем передатчикам излучать мысль</fileid>
  <fileid id="z0001_233">лебедь это лебедь сен санса</fileid>
  <fileid id="z0001_234">но у тебя была еще вторая просьба</fileid>
  <fileid id="z0001_235">если уж в кофейнях шепчутся перед мобилизацией и ни один не идет дело швах</fileid>
  <fileid id="z0001_236">весь чистый сбор поступит монтеру мечникову</fileid>
  <fileid id="z0001_237">это ему наказание за ридикюль</fileid>
  <fileid id="z0001_238">а позвольте дорогие друзья почествовать вас бутылочкой абрашки</fileid>
  <fileid id="z0001_239">шульгин жил самым широким барином очень роскошно</fileid>
  <fileid id="z0001_240">а трупакин решил съездить в клуб</fileid>
  <fileid id="z0001_241">он комбинировал объявления в старгородской правде</fileid>
  <fileid id="z0001_242">кто то выбил револьвер из его рук</fileid>
  <fileid id="z0001_243">как же я теперь остановлюсь</fileid>
  <fileid id="z0001_244">ночевали они в горских саклях</fileid>
  <fileid id="z0001_245">вернется он сюда как же</fileid>
  <fileid id="z0001_246">свисающая ручка на ней петля</fileid>
  <fileid id="z0001_247">венки из полевых цветов у ручья</fileid>
  <fileid id="z0001_248">на дерби он на целый корпус обошел мак магона</fileid>
  <fileid id="z0001_249">но он не запугает меня</fileid>
  <fileid id="z0001_250">вы оперу майская ночь слышали</fileid>
  <fileid id="z0001_251">поэтому тираж решили начать в десять часов</fileid>
  <fileid id="z0001_252">без всяких кистей и глазетов</fileid>
  <fileid id="z0001_253">самый же дом отдан жене его с детьми</fileid>
  <fileid id="z0001_254">с чего вы взяли что он кинжал</fileid>
  <fileid id="z0001_255">командир сделал шаг к бэйли</fileid>
  <fileid id="z0001_256">надо же ж пить же ж</fileid>
  <fileid id="z0001_257">несет меня вьюга как листок</fileid>
  <fileid id="z0001_258">ну вот я и разлюбил тебя</fileid>
  <fileid id="z0001_259">пока что идем вкусить от местных блюд</fileid>
  <fileid id="z0001_260">шоферы дышали горячим бензином и гневом</fileid>
  <fileid id="z0001_261">да зачем же такую уйму</fileid>
  <fileid id="z0001_262">она опять думала об отце</fileid>
  <fileid id="z0001_263">остапу пришлось пересечь весь город</fileid>
  <fileid id="z0001_264">афиша набрана сверстана и отпечатана в школе</fileid>
  <fileid id="z0001_265">что ж и без меня проживете</fileid>
  <fileid id="z0001_266">я вас мерзавцев всех обнаружу</fileid>
  <fileid id="z0001_267">ты чем хочешь быть писателем</fileid>
  <fileid id="z0001_268">в антракте концессионеры прочли афишу</fileid>
  <fileid id="z0001_269">кроме детей здесь жили обезьяны</fileid>
  <fileid id="z0001_270">который месяц я без места</fileid>
  <fileid id="z0001_271">так ведь русских всегда бьют</fileid>
  <fileid id="z0001_272">все ж таки она меня кормит обувает</fileid>
  <fileid id="z0001_273">сжалься о сжалься ты над ней</fileid>
  <fileid id="z0001_274">этот актер был необходим для райка</fileid>
  <fileid id="z0001_275">он был дерзок и смел</fileid>
  <fileid id="z0001_276">нет ничего бескорыстнее детской дружбы</fileid>
  <fileid id="z0001_277">я есть большой замерзавец на свой хрупкий организм</fileid>
  <fileid id="z0001_278">не выпить ли нам пива</fileid>
  <fileid id="z0001_279">никаких прав я не предъявляю</fileid>
  <fileid id="z0001_280">сесть бы в уголочке да помечтать</fileid>
  <fileid id="z0001_281">уж раз сказал что дам то дам</fileid>
  <fileid id="z0001_282">он пил без конца и не мог выпить</fileid>
  <fileid id="z0001_283">дал я ему волчью шубу</fileid>
  <fileid id="z0001_284">швейцар дружелюбно подмигнул мне и хихикнул в кулак</fileid>
  <fileid id="z0001_285">сонной рыбьей стайкой сбились в угол окурки</fileid>
  <fileid id="z0001_286">поезд стоит здесь пять минут</fileid>
  <fileid id="z0001_287">ну дай ему бог смягчилась нянька</fileid>
  <fileid id="z0001_288">квадратная сажень земли стоит пятьдесят</fileid>
  <fileid id="z0001_289">на владимирской улице уже развеваются трехцветные флаги</fileid>
  <fileid id="z0001_290">и пусть там что то разлетелось вдребезги все равно</fileid>
  <fileid id="z0001_291">это имело весьма малый успех</fileid>
  <fileid id="z0001_292">у ипполита матвеевича обвисли руки</fileid>
  <fileid id="z0001_293">немцы вежливы но итальянцы гораздо вежливее</fileid>
  <fileid id="z0001_294">эльза выходит замуж за зауера</fileid>
  <fileid id="z0001_295">после таких слов я застрелюсь</fileid>
  <fileid id="z0001_296">ярость отца федора все увеличивалась</fileid>
  <fileid id="z0001_297">гости мои ушли в свой флигель</fileid>
  <fileid id="z0001_298">муж гусар ее в мундир</fileid>
  <fileid id="z0001_299">сфера женщины все изящное женственное</fileid>
  <fileid id="z0001_300">да ну вас всех к черту</fileid>
  <fileid id="z0001_301">лишь звезды блеснут в небесах</fileid>
  <fileid id="z0001_302">так чего же вы лезете</fileid>
  <fileid id="z0001_303">мы вышли из земной атмосферы</fileid>
  <fileid id="z0001_304">через пять минут мы были уже на аэро</fileid>
  <fileid id="z0001_305">если б дождик мое счастье</fileid>
  <fileid id="z0001_306">в останкине как говорит биограф</fileid>
  <fileid id="z0001_307">весь верхний этаж залит солнцем</fileid>
  <fileid id="z0001_308">здесь его видел поэт князь</fileid>
  <fileid id="z0001_309">старичонка скорченного геморроидами взял под караул</fileid>
  <fileid id="z0001_310">в тишине явственное жужжание колес как шум воспаленной крови</fileid>
  <fileid id="z0001_311">весь город шуршит об этом</fileid>
  <fileid id="z0001_312">и под все завертелось не дам</fileid>
  <fileid id="z0001_313">возьмите это и пропейте за букву а</fileid>
  <fileid id="z0001_314">весь восьмой этаж отведен под жидкий гелий очень ценный продукт</fileid>
  <fileid id="z0001_315">вам этот авессалом голову оторвет</fileid>
  <fileid id="z0001_316">все обступили его и он начал объяснять</fileid>
  <fileid id="z0001_317">писать решили здесь же и сейчас же</fileid>
  <fileid id="z0001_318">я вовсе письмоводитель петр сидоров</fileid>
  <fileid id="z0001_319">у вас что нибудь болит</fileid>
  <fileid id="z0001_320">какой же в этом ужас</fileid>
  <fileid id="z0001_321">ведь не последний же день вместе</fileid>
  <fileid id="z0001_322">пойди займись чем нибудь другим</fileid>
  <fileid id="z0001_323">за ночь холод был съеден без остатка</fileid>
  <fileid id="z0001_324">я не из их числа</fileid>
  <fileid id="z0001_325">маменька позволила мне променять мои серьги</fileid>
  <fileid id="z0001_326">вы на эту сторону плюньте</fileid>
  <fileid id="z0001_327">пока соберемся пока гондола доползет</fileid>
  <fileid id="z0001_328">семьдесят эта историческая коллекция теперь принадлежит</fileid>
  <fileid id="z0001_329">вот я рассказал этот эпизод</fileid>
  <fileid id="z0001_330">в ней есть что то нездешнее</fileid>
  <fileid id="z0001_331">она морщит нос и рычит</fileid>
  <fileid id="z0001_332">наконец то кристо увидит его</fileid>
  <fileid id="z0001_333">шла погрузка парохода антон рубинштейн стоявшего у дебаркадера два</fileid>
  <fileid id="z0001_334">рудольф готлиб вы не ошиблись</fileid>
  <fileid id="z0001_335">нынче вечером я пришлю роль</fileid>
  <fileid id="z0001_336">изнуренков вился вокруг остапа как пчела</fileid>
  <fileid id="z0001_337">с ними было бы легко</fileid>
  <fileid id="z0001_338">мы пользуясь отпуском решили поохотиться в здешних местах на львов</fileid>
  <fileid id="z0001_339">визги и скрежет сменились жужжанием</fileid>
  <fileid id="z0001_340">сейчас ты энергичный умный мальчик</fileid>
  <fileid id="z0001_341">откуда идет обычай снимать шапки перед ними зодчий петр медиоланский</fileid>
  <fileid id="z0001_342">печаль же радости залог</fileid>
  <fileid id="z0001_343">а у жены то были ведь деньги</fileid>
  <fileid id="z0001_344">он всегда конфузился если приходилось беседовать с людьми</fileid>
  <fileid id="z0001_345">я начал впадать в оцепенение</fileid>
  <fileid id="z0001_346">да откуда же я денег то возьму</fileid>
  <fileid id="z0001_347">что ж ты можешь писать о россии</fileid>
  <fileid id="z0001_348">босяки здесь ни при чем</fileid>
  <fileid id="z0001_349">жизнь при царе алексее михайловиче</fileid>
  <fileid id="z0001_350">если могу быть чем нибудь полезен</fileid>
  <fileid id="z0001_351">надо было думать о ночлеге</fileid>
  <fileid id="z0001_352">и как мы над трупом ребенка рыдаем</fileid>
  <fileid id="z0001_353">а мать то мать то</fileid>
  <fileid id="z0001_354">а ваш мальчик меня языком дразнил</fileid>
  <fileid id="z0001_355">я их чуть не поубивал потом</fileid>
  <fileid id="z0001_356">круги становились все меньше мы опускались все глубже</fileid>
  <fileid id="z0001_357">отрывки мыслей наброски схем сделанные торопливой рукой</fileid>
  <fileid id="z0001_358">не забудьте ньютон исаак отчества не помню</fileid>
  <fileid id="z0001_359">а тот пещерный медведь сзади телохранитель</fileid>
  <fileid id="z0001_360">когда вы научитесь быть хозяйкой</fileid>
  <fileid id="z0001_361">хам закричал виктор михайлович вслед шествию</fileid>
  <fileid id="z0001_362">тем более что я теперь каждый почти день бываю в скетинг ринге</fileid>
  <fileid id="z0001_363">да домой уж ехать спать</fileid>
  <fileid id="z0001_364">о яблоньке и ее физических и душевных свойствах</fileid>
  <fileid id="z0001_365">тебя такой вещью не проберешь</fileid>
  <fileid id="z0001_366">при виде полесова кислярский чернел</fileid>
  <fileid id="z0001_367">поезд отходит в десять сорок пять</fileid>
  <fileid id="z0001_368">очень очень милый очень способный</fileid>
  <fileid id="z0001_369">в руках трагедии у них</fileid>
  <fileid id="z0001_370">ну на службе возьми аванс</fileid>
  <fileid id="z0001_371">где то он теперь рыщет</fileid>
  <fileid id="z0001_372">бюллетень за бюллетенем приносили вести о непрестанном понижении курсов</fileid>
  <fileid id="z0001_373">ишь ты проклятая подушку грызет</fileid>
  <fileid id="z0001_374">нельзя вечно идти на поводу англии</fileid>
  <fileid id="z0001_375">душилов впал в унылое раздумье</fileid>
  <fileid id="z0001_376">вот и пятистишие по его адресу</fileid>
  <fileid id="z0001_377">и это нам всем печально</fileid>
  <fileid id="z0001_378">а в то время очень огорчался</fileid>
  <fileid id="z0001_379">и остап вынул из кармана маленькое позолоченное ситечко</fileid>
  <fileid id="z0001_380">теперь я бегу почти наравне с медведицей</fileid>
  <fileid id="z0001_381">но зацепиться за них было немыслимо</fileid>
  <fileid id="z0001_382">ты так мало со мной видишься людвиг</fileid>
  <fileid id="z0001_383">остап вытер свой благородный лоб</fileid>
  <fileid id="z0001_384">но об этом говорит весь мир</fileid>
  <fileid id="z0001_385">наконец сердце его не выдерживало</fileid>
  <fileid id="z0001_386">море и любовь не терпят педантов</fileid>
  <fileid id="z0001_387">да удобно ли мне дядюшка</fileid>
  <fileid id="z0001_388">сцена была убрана с небывалою роскошью</fileid>
  <fileid id="z0001_389">я весь кинулся в узенький белый прорез и</fileid>
  <fileid id="z0001_390">друг ты мне или нет</fileid>
  <fileid id="z0001_391">еще через год здесь был бы целый монблан</fileid>
  <fileid id="z0001_392">дружина первая пехотная третий ее отдел</fileid>
  <fileid id="z0001_393">острый нож я вколол в горло и обмер</fileid>
  <fileid id="z0001_394">тут стало быть апостол петр</fileid>
  <fileid id="z0001_395">на эстраду вышел сдобный мужчина в визитке и лаковых туфлях</fileid>
  <fileid id="z0001_396">вам лицо бюст или тело</fileid>
  <fileid id="z0001_397">он мне теперь не друг</fileid>
  <fileid id="z0001_398">великий комбинатор был прав как всегда</fileid>
  <fileid id="z0001_399">сальватор крепко пожал руку кристо</fileid>
  <fileid id="z0001_400">но закричал я захлопав вожжами</fileid>
  <fileid id="z0001_401">дело салтычихи тянулось шесть лет</fileid>
  <fileid id="z0001_402">а купчишки теперь так дерут что приступу ни к чему нет</fileid>
  <fileid id="z0001_403">где то сзади я слышал пронзительный писк птиц над стеной</fileid>
  <fileid id="z0001_404">а там происходил последний акт борьбы</fileid>
  <fileid id="z0001_405">из ворот выбегали домашние хозяйки</fileid>
  <fileid id="z0001_406">а давыдов сто тридцать пять хоть не пой</fileid>
  <fileid id="z0001_407">они очень нуждаются в билетах</fileid>
  <fileid id="z0001_408">у меня как раз цинга</fileid>
  <fileid id="z0001_409">нет ли у вас второго револьвера</fileid>
  <fileid id="z0001_410">мы и так стали ужасно малокровные от блохи</fileid>
  <fileid id="z0001_411">авторы этого зрелища волков сумароков и херасков</fileid>
  <fileid id="z0001_412">в следующем году он заказал такой шрифт в амстердаме</fileid>
  <fileid id="z0001_413">раскиданный на мгновенные несвязные обломки мир</fileid>
  <fileid id="z0001_414">и будешь ты царицей мира</fileid>
  <fileid id="z0001_415">сейчас бы кюрассо был к месту</fileid>
  <fileid id="z0001_416">нашли дурака грека с деньгами</fileid>
  <fileid id="z0001_417">человек также по видимому увидал нас и начал размахивать руками</fileid>
  <fileid id="z0001_418">говоришь и вдруг понесешь чепуху</fileid>
  <fileid id="z0001_419">терпишь долго а потом прорвется</fileid>
  <fileid id="z0001_420">не надо ли им чего</fileid>
  <fileid id="z0001_421">наша яхта не поднимет всех этих гостей</fileid>
  <fileid id="z0001_422">дочь графа орлова графиня анна алексеевна</fileid>
  <fileid id="z0001_423">это я тень так сделал</fileid>
  <fileid id="z0001_424">особенно здесь торжественно праздновался день тринадцатого мая</fileid>
  <fileid id="z0001_425">поведи его в кинематограф или еще куда</fileid>
  <fileid id="z0001_426">а теперь что прикажешь делать</fileid>
  <fileid id="z0001_427">сказал он и дал шпоры</fileid>
  <fileid id="z0001_428">впрочем можно и в первом</fileid>
  <fileid id="z0001_429">на другой день весь театр колумба сидел в буфете курского вокзала</fileid>
  <fileid id="z0001_430">был один господин здесь без тебя</fileid>
  <fileid id="z0001_431">по улице шагал с самым рассеянным видом</fileid>
  <fileid id="z0001_432">под конец своей жизни гераков жил у князя</fileid>
  <fileid id="z0001_433">и смелые философы непременно дети</fileid>
  <fileid id="z0001_434">генерал повернул лошадь к площади и изо всех сил вонзил шпоры в бока</fileid>
  <fileid id="z0001_435">мадам грицацуева бендер в страхе кинулась к дверям</fileid>
  <fileid id="z0001_436">а сегодня утром выехали в семь утра</fileid>
  <fileid id="z0001_437">теперь уж машина завертелась без тебя</fileid>
  <fileid id="z0001_438">о видите ли сказал горький есть два неаполя</fileid>
  <fileid id="z0001_439">невысокие жигулевские горы мощно зеленели с правой стороны</fileid>
  <fileid id="z0001_440">мое ружье опять дало осечку</fileid>
  <fileid id="z0001_441">хи хи запищал голый гришка</fileid>
  <fileid id="z0001_442">если нет так выгоняйте уж сразу</fileid>
  <fileid id="z0001_443">в конке нам пришлось сидеть рядом</fileid>
  <fileid id="z0001_444">я только был вежлив как со всеми прочими</fileid>
  <fileid id="z0001_445">в одном письме вероятно в начале этой любви мазепа пишет</fileid>
  <fileid id="z0001_446">в ваших глазах есть что то такое магнетическое</fileid>
  <fileid id="z0001_447">и вдруг тишину вновь нарушил звук трубы и крик</fileid>
  <fileid id="z0001_448">треухов мечтал о большом деле</fileid>
  <fileid id="z0001_449">стихи чрезвычайно приятные и освежительны для ума</fileid>
  <fileid id="z0001_450">ты сама об этом мечтала давеча</fileid>
  <fileid id="z0001_451">в чем дело мистер люк</fileid>
  <fileid id="z0001_452">по дороге он завернул в аптеку</fileid>
  <fileid id="z0001_453">теперь целый день буду играть</fileid>
  <fileid id="z0001_454">заговорщики тщательно хранили доверенную им тайну</fileid>
  <fileid id="z0001_455">я возьму тебя с собой</fileid>
  <fileid id="z0001_456">но теперь мы в блокаде</fileid>
  <fileid id="z0001_457">в степенной книге приведена речь царя</fileid>
  <fileid id="z0001_458">а ну поправь ка ей бок</fileid>
  <fileid id="z0001_459">но сальватор обманет пообещает выкуп и не даст</fileid>
  <fileid id="z0001_460">дери с нас за корзины</fileid>
  <fileid id="z0001_461">за час до отхода поезда вернулся на вокзал</fileid>
  <fileid id="z0001_462">ну мотечка не сердись на нас</fileid>
  <fileid id="z0001_463">а поутру она вновь улыбалась высокий класс</fileid>
  <fileid id="z0001_464">государыне очень понравилось здание дворца</fileid>
  <fileid id="z0001_465">восемь рублей в первом ряду прямо</fileid>
  <fileid id="z0001_466">его могло спасти только завоевание иностранных рынков</fileid>
  <fileid id="z0001_467">о да мистер бэйли преступник</fileid>
  <fileid id="z0001_468">знаешь что сядем на эту ночь в караул</fileid>
  <fileid id="z0001_469">ровно в полдень запел петух в кооперативе плуг и молот</fileid>
  <fileid id="z0001_470">то поэт наш карин милый</fileid>
  <fileid id="z0001_471">он меня хватал за руку</fileid>
  <fileid id="z0001_472">теперь они принялись изучать берег</fileid>
  <fileid id="z0001_473">я беру тебя на службу</fileid>
  <fileid id="z0001_474">была ли это ася званцева</fileid>
  <fileid id="z0001_475">грабят шепотом сказал незнакомец еще крепче держась за стул</fileid>
  <fileid id="z0001_476">викинга отвели от столба стегнули и он вновь пошел</fileid>
  <fileid id="z0001_477">строганова репнина шувалова и еще некоторых других вельмож</fileid>
  <fileid id="z0001_478">ковалевский автор книги граф блудов</fileid>
  <fileid id="z0001_479">покупка екатериной имения черная грязь</fileid>
  <fileid id="z0001_480">корнфельдом было выпущено на рынок свыше двух миллионов книг</fileid>
  <fileid id="z0001_481">перебросьте сюда тридцать пять рублей</fileid>
  <fileid id="z0001_482">дюжина товарных рязано уральской дороги</fileid>
  <fileid id="z0001_483">вот один из таких шагов</fileid>
  <fileid id="z0001_484">я делал вид что не замечаю этих ухищрений</fileid>
  <fileid id="z0001_485">у них что нибудь случилось</fileid>
  <fileid id="z0001_486">иначе бы я не мог и рта раскрыть</fileid>
  <fileid id="z0001_487">авось там удастся вскрыть стулья</fileid>
  <fileid id="z0001_488">куплен сегодня утром за три рубля</fileid>
  <fileid id="z0001_489">а я как перед господом</fileid>
  <fileid id="z0001_490">где ваш муж служил нервно спросил потылицын</fileid>
  <fileid id="z0001_491">приготовьте гришу ко всему этому</fileid>
  <fileid id="z0001_492">а раз начнем госбанк и комбанк дадут ссуду</fileid>
  <fileid id="z0001_493">на первый день пасхи пойдем увидишь</fileid>
  <fileid id="z0001_494">вы в силах поднять руку</fileid>
  <fileid id="z0001_495">большая экскурсия вошла в подъезд</fileid>
  <fileid id="z0001_496">теперь вся сила в гемоглобине</fileid>
  <fileid id="z0001_497">неужели в деньгах все дело</fileid>
  <fileid id="z0001_498">репертуар вообще весь русский репертуар был слаб и скуден</fileid>
  <fileid id="z0001_499">что же теперь будет воробьянинов спросил савицкий</fileid>
  <fileid id="z0001_500">нет зуб пока не нужно</fileid>
  <fileid id="z0001_501">должно быть все это орет каркает жужжит</fileid>
  <fileid id="z0001_502">спасибо я вам очень обязан</fileid>
  <fileid id="z0001_503">нет к счастью не бред</fileid>
  <fileid id="z0001_504">это ведь жене месяц жизни в крыму</fileid>
  <fileid id="z0001_505">есть у нас что нибудь</fileid>
  <fileid id="z0001_506">я сегодня весь день на ногах</fileid>
  <fileid id="z0001_507">друг мой умер в эту ночь</fileid>
  <fileid id="z0001_508">тогда то я еще о биноклях и не слыхивал</fileid>
  <fileid id="z0001_509">сестренку труську целый день ведь лижет</fileid>
  <fileid id="z0001_510">ты же лошадь же ж</fileid>
  <fileid id="z0001_511">через час зоофилов стал устраиваться на ночлег</fileid>
  <fileid id="z0001_512">так что ж записывать тебя</fileid>
  <fileid id="z0001_513">больше всех был в восторге наш возница</fileid>
  <fileid id="z0001_514">да ведь лопнет же все это завопил мотылек</fileid>
  <fileid id="z0001_515">ну а как поживает ваш сынок миша</fileid>
  <fileid id="z0001_516">штирнер и эльза спустились к берегу</fileid>
  <fileid id="z0001_517">я не мог выдержать больше</fileid>
  <fileid id="z0001_518">я заплатила бы ваши долги</fileid>
  <fileid id="z0001_519">сиди дома и не рыпайся</fileid>
  <fileid id="z0001_520">я братец мой товарищ хороший</fileid>
  <fileid id="z0001_521">а вы бы спать лучше пошли</fileid>
  <fileid id="z0001_522">и будут вымаливать маленький глоточек</fileid>
  <fileid id="z0001_523">давайте плоскогубцы крикнул он остапу</fileid>
  <fileid id="z0001_524">но ведь у него мозги чугунные</fileid>
  <fileid id="z0001_525">он конечно приставлен шпионить за мной</fileid>
  <fileid id="z0001_526">греч в своих записках говорит</fileid>
  <fileid id="z0001_527">князь вяземский в своих записках говорит</fileid>
  <fileid id="z0001_528">стул будет стоять здесь до ночи</fileid>
  <fileid id="z0001_529">он хочет в норвегию а я в ниццу</fileid>
  <fileid id="z0001_530">лухманова на них съезжалась смотреть вся москва</fileid>
  <fileid id="z0001_531">на крестце в китай город</fileid>
  <fileid id="z0001_532">в настоящее время в чебоксарах семь тысяч семьсот два жителя</fileid>
  <fileid id="z0001_533">посиневшие ладони зашлепали зашарили по изразцам</fileid>
  <fileid id="z0001_534">вы знаете что такое алиби</fileid>
  <fileid id="z0001_535">вызвать на дуэль мужа за что</fileid>
  <fileid id="z0001_536">очень поучительное зрелище не правда ли</fileid>
  <fileid id="z0001_537">и впряг огонь в машину сталь</fileid>
  <fileid id="z0001_538">не будет им за это елки</fileid>
  <fileid id="z0001_539">в морщинах весь а ругается</fileid>
  <fileid id="z0001_540">хочу чтоб сардинки были мои</fileid>
  <fileid id="z0001_541">в дверь втиснулась фигура в бараньей шубе валенках</fileid>
  <fileid id="z0001_542">друзья вступили в гулкий вестибюль театра колумба</fileid>
  <fileid id="z0001_543">а мать грозит ему в окно</fileid>
  <fileid id="z0001_544">брось что нибудь на пол</fileid>
  <fileid id="z0001_545">я признаться не при деньгах</fileid>
  <fileid id="z0001_546">жаловаться на сальватора в буэнос айрес</fileid>
  <fileid id="z0001_547">по мне хоть всю жизнь живи раз хороший человек</fileid>
  <fileid id="z0001_548">от грудки отрежьте и эту ножку</fileid>
  <fileid id="z0001_549">стул никем не поддерживаемый свалился на битый кирпич</fileid>
  <fileid id="z0001_550">в этот день весь париж на улице</fileid>
  <fileid id="z0001_551">что вы делаете удивленно сказал муж саша</fileid>
  <fileid id="z0001_552">мистер клименко ожег себе руку</fileid>
  <fileid id="z0001_553">никола да ты даже в рифму умеешь сочинять</fileid>
  <fileid id="z0001_554">я так счастлива так счастлива</fileid>
  <fileid id="z0001_555">какого перекопу тщетно напрягая свой бедный земной ум спросил турбин</fileid>
  <fileid id="z0001_556">да зачем вам телесный цвет</fileid>
  <fileid id="z0001_557">ни в жизнь на вас тень я не брошу</fileid>
  <fileid id="z0001_558">деповцы загоняли паровоз в стойло</fileid>
  <fileid id="z0001_559">прошел с лихвой первый двадцатиоднодневный знаменитый срок</fileid>
  <fileid id="z0001_560">солнце лежало на персиковой обивке кресел</fileid>
  <fileid id="z0001_561">ну и бог с ней</fileid>
  <fileid id="z0001_562">а теперь медали за дворницкую службу дают</fileid>
  <fileid id="z0001_563">полегче полегче и так уж розовой водицей пишу</fileid>
  <fileid id="z0001_564">постарайтесь развлечься встречайтесь с другими женщинами увлекайтесь ими</fileid>
  <fileid id="z0001_565">новакович глянул хищным оком на шашлыки и простонал</fileid>
  <fileid id="z0001_566">а ведь мы сейчас именно так</fileid>
  <fileid id="z0001_567">петровский дворец казаков выстроил в семь лет</fileid>
  <fileid id="z0001_568">что ж мне с вами делать все таки</fileid>
  <fileid id="z0001_569">именно я и хотел отказаться от второй рюмки</fileid>
  <fileid id="z0001_570">наконец кровь утихла и я вымазал яму в челюсти йодом</fileid>
  <fileid id="z0001_571">но зачем теперь мне этот домик</fileid>
  <fileid id="z0001_572">боже как быстро жизнь мчится</fileid>
  <fileid id="z0001_573">это рудольф готлиб выбрил меня</fileid>
  <fileid id="z0001_574">из ваших же собственных слов</fileid>
  <fileid id="z0001_575">все это конечно очень мило и над всем царствует гетман</fileid>
  <fileid id="z0001_576">в самом деле такой загадки не задавал египетский сфинкс</fileid>
  <fileid id="z0001_577">мы сумеем вернуть им ценность</fileid>
  <fileid id="z0001_578">у самцов без шерсти была только часть лица как у наших предков</fileid>
  <fileid id="z0001_579">проживавший тогда в москве</fileid>
  <fileid id="z0001_580">пять деревьев на шесть лошадей</fileid>
  <fileid id="z0001_581">так сажени на полторы от земли</fileid>
  <fileid id="z0001_582">заговорщики поднимались прямо к звездам</fileid>
  <fileid id="z0001_583">товарищ клименко ничего не знает</fileid>
  <fileid id="z0001_584">ну что ж сказал остап громко</fileid>
  <fileid id="z0001_585">она вышла замуж за степана</fileid>
  <fileid id="z0001_586">бросьте наших маклеров скупать эти бумаги</fileid>
  <fileid id="z0001_587">нет музыки нет веселых песен</fileid>
  <fileid id="z0001_588">не правда ли я похож теперь на старца пустынника</fileid>
  <fileid id="z0001_589">в отчаянии рудольф бросился к эльзе глюк</fileid>
  <fileid id="z0001_590">надо ж купаться же ж</fileid>
  <fileid id="z0001_591">леночка я взял билет на аиду</fileid>
  <fileid id="z0001_592">с каких это пор вы стали говорить комплименты</fileid>
  <fileid id="z0001_593">он первое время несомненно тосковал без хвоста</fileid>
  <fileid id="z0001_594">ведь впереди еще был бифштекс по гамбургски не забывайте этого</fileid>
  <fileid id="z0001_595">ни шиша о это очень мило</fileid>
  <fileid id="z0001_596">в кооперативную флейту гаврила был сдан под названием эолова флейта</fileid>
  <fileid id="z0001_597">садитесь рядом с девочкой и сидите</fileid>
  <fileid id="z0001_598">смерть графини и трогательная печаль графа</fileid>
  <fileid id="z0001_599">покажите мне не жгучий огонь</fileid>
  <fileid id="z0001_600">ты парень может быть и неглупый да только не на немецкой почве</fileid>
  <fileid id="z0001_601">я впрыснул ей морфий успокоилась</fileid>
  <fileid id="z0001_602">а потом как лопнул гной вытек</fileid>
  <fileid id="z0001_603">корсаков навлек гнев государыни похитив жену графа а</fileid>
  <fileid id="z0001_604">и чрезвычайно счастлив если получит ответ</fileid>
  <fileid id="z0001_605">она оказалась тяжелой и толстой как дверь несгораемого шкафа</fileid>
  <fileid id="z0001_606">покажут вам и курение и стрельбу и бродяжничество</fileid>
  <fileid id="z0001_607">так хочется посидеть часик совсем одному</fileid>
  <fileid id="z0001_608">тогда можно было а теперь нельзя</fileid>
  <fileid id="z0001_609">но теперь к этому очарованию примешивалась печаль об утерянном счастье</fileid>
  <fileid id="z0001_610">удержите ваше сердце от терзаний мужчина должен уметь сделать это</fileid>
  <fileid id="z0001_611">об чем спор повторил он</fileid>
  <fileid id="z0001_612">нет вы эти старые штуки оставьте</fileid>
  <fileid id="z0001_613">очевидно бэйли решил разъединить нас</fileid>
  <fileid id="z0001_614">это я весной засунула их сюда перед пасхой</fileid>
  <fileid id="z0001_615">отто зауер забыл портфель и идет за ним мелькнула у нее мысль</fileid>
  <fileid id="z0001_616">старопечатных книг много было</fileid>
  <fileid id="z0001_617">ты врешь неожиданно сказал угольщик</fileid>
  <fileid id="z0001_618">и на помощь я звать не буду</fileid>
  <fileid id="z0001_619">тихо сказал остап нужно действовать без шума</fileid>
  <fileid id="z0001_620">ваш редактор оказался очень симпатичным</fileid>
  <fileid id="z0001_621">через семь месяцев нас будет уже трое</fileid>
  <fileid id="z0001_622">она вставала и подходила к зеркалу</fileid>
  <fileid id="z0001_623">в ночь перед отлетом штирнер не спал</fileid>
  <fileid id="z0001_624">зачем я сунулся к нему со щипцами</fileid>
  <fileid id="z0001_625">теперь вообще ведь всюду рисунок упал</fileid>
  <fileid id="z0001_626">это очень беспокоило ипполита матвеевича</fileid>
  <fileid id="z0001_627">он на коралл ни капельки не похож</fileid>
  <fileid id="z0001_628">тоска обвилась вокруг моего сердца</fileid>
  <fileid id="z0001_629">от этого и сыпь на груди</fileid>
  <fileid id="z0001_630">в окне сиял один из первых зимних дней</fileid>
  <fileid id="z0001_631">а добрился я в девять вечера</fileid>
  <fileid id="z0001_632">ревизор часто часто потер руки одна о другую</fileid>
  <fileid id="z0001_633">на сорок восемь тысяч двести тридцать восемь литера в</fileid>
  <fileid id="z0001_634">вам хочется скорее видеть подстреленными этих птиц</fileid>
  <fileid id="z0001_635">это в довесочек к десяткам тысяч мужичков</fileid>
  <fileid id="z0001_636">но я не могу судить вас без улик</fileid>
  <fileid id="z0001_637">что ж хлеб тут сеешь что ли</fileid>
  <fileid id="z0001_638">нарышкин был в ссоре с канцлером румянцевым</fileid>
  <fileid id="z0001_639">в огороде бузина а в киеве дядька</fileid>
  <fileid id="z0001_640">церковь чуда архангела михаила в чудовом монастыре в кремле</fileid>
  <fileid id="z0001_641">я мог бы скрутить вас теперь в бараний рог</fileid>
  <fileid id="z0001_642">морфий помог быстрее чем я ожидал</fileid>
  <fileid id="z0001_643">а сбоку подходит француз метрдотель и говорит мило грассируя</fileid>
  <fileid id="z0001_644">но может быть отец ее не отдаст</fileid>
  <fileid id="z0001_645">куда вы теперь пойдете с этой зеленой липой</fileid>
  <fileid id="z0001_646">куда же ты их дел</fileid>
  <fileid id="z0001_647">руки не повиновались когда она вскрывала конверт</fileid>
  <fileid id="z0001_648">ведь и глупенькие хотят счастья</fileid>
  <fileid id="z0001_649">первое выкиньте с корнем молитву</fileid>
  <fileid id="z0001_650">лед тронулся закричал остап машинисту</fileid>
  <fileid id="z0001_651">ты угрожающе зарычал тарарыкин</fileid>
  <fileid id="z0001_652">без индейской хитрости с этими людьми ничего не сделаешь</fileid>
  <fileid id="z0001_653">очень будем рады с мужем видеть вас</fileid>
  <fileid id="z0001_654">жил я все время у дяди дядя у меня мельник а теперь места приехал искать</fileid>
  <fileid id="z0001_655">но его сердце занято эльзой</fileid>
  <fileid id="z0001_656">остап все время произносил речи спичи и тосты</fileid>
  <fileid id="z0001_657">ведь что же это такое</fileid>
  <fileid id="z0001_658">язык у него и прилипнет к гортани</fileid>
  <fileid id="z0001_659">здесь между ним и треуховым вспыхивали перебранки</fileid>
  <fileid id="z0001_660">я не переношу таких форм безумия</fileid>
  <fileid id="z0001_661">ипполит матвеевич подбежал к нему</fileid>
  <fileid id="z0001_662">остап посмотрел вниз на толпу</fileid>
  <fileid id="z0001_663">на ловца как говорится и зверь бежит</fileid>
  <fileid id="z0001_664">если беда так пойдем на помощь</fileid>
  <fileid id="z0001_665">еще если лет восемьсот девятьсот</fileid>
  <fileid id="z0001_666">шиканье и свистки покрыли речь неофутуриста</fileid>
  <fileid id="z0001_667">ну его к бесу ваш пиджак</fileid>
  <fileid id="z0001_668">я знаю тысяч десять лир</fileid>
  <fileid id="z0001_669">ипполит матвеевич поднял лицо и обмер</fileid>
  <fileid id="z0001_670">старик мелко задребезжал виляя позвоночником</fileid>
  <fileid id="z0001_671">это ведь о нас о теперь</fileid>
  <fileid id="z0001_672">кошка подумал я и зажег свет</fileid>
  <fileid id="z0001_673">так мотька отвлекся что я день и ночь плачу</fileid>
  <fileid id="z0001_674">идите уж себе простонал сандомирский</fileid>
  <fileid id="z0001_675">горничная почуяла под собой почву</fileid>
  <fileid id="z0001_676">и опять покорно фельдшер впрыснул масло</fileid>
  <fileid id="z0001_677">ты у меня будешь знать</fileid>
  <fileid id="z0001_678">а он все таки здесь</fileid>
  <fileid id="z0001_679">выясняли очередность ухода в отпуск</fileid>
  <fileid id="z0001_680">штирнер вышел из зимнего сада</fileid>
  <fileid id="z0001_681">а какую вещь я начал</fileid>
  <fileid id="z0001_682">сквозь зубы на ухо мне</fileid>
  <fileid id="z0001_683">но он любил и меня мое сердце не обманешь</fileid>
  <fileid id="z0001_684">первый из них был сын пензенского вице губернатора</fileid>
  <fileid id="z0001_685">вы только кажется и думаете что о киндякиных</fileid>
  <fileid id="z0001_686">что о грозно заревел новакович</fileid>
  <fileid id="z0001_687">в ней хранились листки испещренные математическими вычислениями и формулами</fileid>
  <fileid id="z0001_688">не люблю поощрять его гомерическую лень</fileid>
  <fileid id="z0001_689">я понял мысль мистера бэйли</fileid>
  <fileid id="z0001_690">и вот бледнеющий над рифмами шишков</fileid>
  <fileid id="z0001_691">вот не хочется и все</fileid>
  <fileid id="z0001_692">мне что то не хочется</fileid>
  <fileid id="z0001_693">мир праху вашему краснобаи и обманщики</fileid>
  <fileid id="z0001_694">я кряхтел курил пил черный холодный чай</fileid>
  <fileid id="z0001_695">он подрядил трудолюбивого переводчика</fileid>
  <fileid id="z0001_696">кровь хлестнула мне в лицо</fileid>
  <fileid id="z0001_697">представьте себе что в таком кавардаке она уцелела</fileid>
  <fileid id="z0001_698">не будет того эффекта произнес остап вслух</fileid>
  <fileid id="z0001_699">он хотел только одного вниз на землю</fileid>
  <fileid id="z0001_700">я например безумно хочу жрать а все закрыто</fileid>
  <fileid id="z0001_701">у нас всего восемь франков</fileid>
  <fileid id="z0001_702">за помощь спасибо а выписывайте завтра</fileid>
  <fileid id="z0001_703">а кем же ты будешь считать меня</fileid>
  <fileid id="z0001_704">впрочем марусю мог бы нянчить и мой никифор</fileid>
  <fileid id="z0001_705">и хунтов писал героические романы</fileid>
  <fileid id="z0001_706">а мне уже под пятьдесят</fileid>
  <fileid id="z0001_707">московский гость был холост и юн</fileid>
  <fileid id="z0001_708">да я много пережил горьких минут фрейлейн</fileid>
  <fileid id="z0001_709">не вспомнишь ли хоть первую букву</fileid>
  <fileid id="z0001_710">в смехе слышалось тоскливое предчувствие собственной гибели</fileid>
  <fileid id="z0001_711">ты меня довел почти до смерти и теперь хочешь говорить о другом</fileid>
  <fileid id="z0001_712">ну дальше там уж техника</fileid>
  <fileid id="z0001_713">к тому же он был тонкий психолог</fileid>
  <fileid id="z0001_714">он видел все маневры концессионеров</fileid>
  <fileid id="z0001_715">король был удивлен великолепием шереметевского имения</fileid>
  <fileid id="z0001_716">ты будешь больной если ты их не прочтешь</fileid>
  <fileid id="z0001_717">ага сказал секретарь очень хорошо</fileid>
  <fileid id="z0001_718">пожить еще один день в венеции</fileid>
  <fileid id="z0001_719">но остап был по прежнему бодр</fileid>
  <fileid id="z0001_720">государь тотчас отгадал мысль матвеева</fileid>
  <fileid id="z0001_721">тем более больших денег это не стоило</fileid>
  <fileid id="z0001_722">левая была снабжена беленькой жестянкой</fileid>
  <fileid id="z0001_723">из за угла показалась растрепанная фигура макаронова</fileid>
  <fileid id="z0001_724">он понял что слезть вниз ему никак не удастся</fileid>
  <fileid id="z0001_725">и еще интересный вопрос почему рудольф и вильям не воспользовались лошадьми а пошли пешком</fileid>
  <fileid id="z0001_726">да ведь этак всю жизнь провозишься</fileid>
  <fileid id="z0001_727">так и стоит без дела</fileid>
  <fileid id="z0001_728">барьеры в большом ходу в учреждениях</fileid>
  <fileid id="z0001_729">через третьих лиц ничего не предпринимать</fileid>
  <fileid id="z0001_730">аннушка в моих пьесах играла</fileid>
  <fileid id="z0001_731">ты выпьешь его в раю</fileid>
  <fileid id="z0001_732">с приездом в поволжский край генерал прокурора князя</fileid>
  <fileid id="z0001_733">лошади у вас живут без сена безобразие</fileid>
  <fileid id="z0001_734">а у франции восемьдесят тысяч боевых самолетов</fileid>
  <fileid id="z0001_735">вот туда идите ухмыльнулся буфетчик</fileid>
  <fileid id="z0001_736">теперь все как то сделалось культурнее</fileid>
  <fileid id="z0001_737">хороший человек чтоб ты сдох</fileid>
  <fileid id="z0001_738">светло засинел вечер а митинг все продолжался</fileid>
  <fileid id="z0001_739">тогда старец встал и проворно вышел из землянки</fileid>
  <fileid id="z0001_740">палец о палец не ударю</fileid>
  <fileid id="z0001_741">государь на его просьбу ответил следующим</fileid>
  <fileid id="z0001_742">сейчас было как у древних перед грозой</fileid>
  <fileid id="z0001_743">одна вещь только меня заботит</fileid>
  <fileid id="z0001_744">даже больше ты философ от математики</fileid>
  <fileid id="z0001_745">ура гаркнул крысаков из под шляпы</fileid>
  <fileid id="z0001_746">отец федор не просит подаяния</fileid>
  <fileid id="z0001_747">и надо всем предостерегающая надпись</fileid>
  <fileid id="z0001_748">через шесть часов дам смену</fileid>
  <fileid id="z0001_749">свидание у источника в полночь</fileid>
  <fileid id="z0001_750">кто ж нынче домой ходит</fileid>
  <fileid id="z0001_751">знакомьтесь со мной сказала айя</fileid>
  <fileid id="z0001_752">как хотите а я обещал что бросите</fileid>
  <fileid id="z0001_753">никола только теперь увидел что мертвец был привязан тонким линем к фальшборту</fileid>
  <fileid id="z0001_754">вот мы уже у меценатова подъезда</fileid>
  <fileid id="z0001_755">очень жаль мы только настроились слушать</fileid>
  <fileid id="z0001_756">не получишь денег заявил наниматель</fileid>
  <fileid id="z0001_757">клотильда пошла из кино в васину мастерскую</fileid>
  <fileid id="z0001_758">жаль лишь что некому было полюбоваться на меня</fileid>
  <fileid id="z0001_759">чтоб вас громом убило паршивцев</fileid>
  <fileid id="z0001_760">но ведь четверг это у нас</fileid>
  <fileid id="z0001_761">я ведь сам от нее ушел</fileid>
  <fileid id="z0001_762">он меня замучил очень тихо сказал врач</fileid>
  <fileid id="z0001_763">богатство и роскошь дома голицына</fileid>
  <fileid id="z0001_764">один щенок родился даже одноглазым</fileid>
  <fileid id="z0001_765">он ему уже не нужен</fileid>
  <fileid id="z0001_766">здесь лесок к себе манит</fileid>
  <fileid id="z0001_767">индеец низко поклонился и протянул ребенка</fileid>
  <fileid id="z0001_768">и еще год пронесся над писателем и его женой</fileid>
  <fileid id="z0001_769">всего два миллиона триста восемь тысяч рублей</fileid>
  <fileid id="z0001_770">но ведь сегодня же суббота</fileid>
  <fileid id="z0001_771">государь заметил заведовавшему театром нарышкину</fileid>
  <fileid id="z0001_772">остап показал рукой на воробьянинова</fileid>
  <fileid id="z0001_773">что мог я еще сделать</fileid>
  <fileid id="z0001_774">однако агафья держалась на сцене прекрасно</fileid>
  <fileid id="z0001_775">и очень хочет вас видеть</fileid>
  <fileid id="z0001_776">жизнь все дешевле и дешевле</fileid>
  <fileid id="z0001_777">что ты думаешь делать дальше кристо</fileid>
  <fileid id="z0001_778">ведь без билета не пустят</fileid>
  <fileid id="z0001_779">оштрафует тебя николай алексеич будешь знать</fileid>
  <fileid id="z0001_780">павлик ваш здоров но скучает</fileid>
  <fileid id="z0001_781">и денег сколько угодно и погулять негде</fileid>
  <fileid id="z0001_782">я люблю вас очень сильно</fileid>
  <fileid id="z0001_783">остап все таки не вставал</fileid>
  <fileid id="z0001_784">в ту ночь не было бури</fileid>
  <fileid id="z0001_785">обыкновенный дождик без грома и молний</fileid>
  <fileid id="z0001_786">в чай я уверен мышьяк подсыпает</fileid>
  <fileid id="z0001_787">о чтоб тебя черти забрали</fileid>
  <fileid id="z0001_788">у тебя даже лоб влажный</fileid>
  <fileid id="z0001_789">а пора уже на что нибудь решиться</fileid>
  <fileid id="z0001_790">клуб был невелик но построен ладно</fileid>
  <fileid id="z0001_791">машины не могли действовать без управления</fileid>
  <fileid id="z0001_792">луч солнца прорезал мои сомкнутые веки и заставил открыть глаза</fileid>
  <fileid id="z0001_793">господь бог хорошо обеспечил этих бездельников</fileid>
  <fileid id="z0001_794">ну что я мог ей сказать</fileid>
  <fileid id="z0001_795">а потом слопаете захрапите и нужен перед носом новый хвост</fileid>
  <fileid id="z0001_796">я ведь себя не предлагаю</fileid>
  <fileid id="z0001_797">любовь была пламенная иссушающая беднягино сердце</fileid>
  <fileid id="z0001_798">с тех пор прошло восемь дней</fileid>
  <fileid id="z0001_799">смех сквозь невидимые миру слезы</fileid>
  <fileid id="z0001_800">не о себе я теперь думаю</fileid>
  <fileid id="z0001_801">нас сейчас двое а через семь месяцев будет трое</fileid>
  <fileid id="z0001_802">здравствуй мерзавец арефьев обыгравший меня в своем притоне</fileid>
  <fileid id="z0001_803">этот звук поразил экипаж медузы как удар грома</fileid>
  <fileid id="z0001_804">это к делу не относится</fileid>
  <fileid id="z0001_805">на постелях бельишко было рваное</fileid>
  <fileid id="z0001_806">семен кириллович был первым щеголем в свое время</fileid>
  <fileid id="z0001_807">а ежели без обтяжки мои господа очень даже как обижаются</fileid>
  <fileid id="z0001_808">сейчас ты вкусил славу любовь женщин и зависть коллег</fileid>
  <fileid id="z0001_809">к чему же тогда салфетка</fileid>
  <fileid id="z0001_810">ему нужен стол на глупых тумбах</fileid>
  <fileid id="z0001_811">неужели ты не видишь сам</fileid>
  <fileid id="z0001_812">кокошкин очень любил чтение вслух и декламацию</fileid>
  <fileid id="z0001_813">ведь это такие ж люди как и мы</fileid>
  <fileid id="z0001_814">а я к вам по делу товарищ щукин</fileid>
  <fileid id="z0001_815">ипполит матвеевич за все время экзекуции не издал ни звука</fileid>
  <fileid id="z0001_816">дорогой константин семь лет ты не был в москве</fileid>
  <fileid id="z0001_817">я вновь побежал нагоняя николу</fileid>
  <fileid id="z0001_818">я не мог еще регулировать свою температуру</fileid>
  <fileid id="z0001_819">только ты можешь все испортить</fileid>
  <fileid id="z0001_820">я всего семь месяцев служу</fileid>
  <fileid id="z0001_821">шубочку то не забудьте захватить</fileid>
  <fileid id="z0001_822">может примочку какую нибудь надо</fileid>
  <fileid id="z0001_823">вам что нибудь нужно фрау</fileid>
  <fileid id="z0001_824">я так и вцепился в него</fileid>
  <fileid id="z0001_825">ведь шубы от этого не убудет</fileid>
  <fileid id="z0001_826">сверху в это время сеяло как сквозь сито</fileid>
  <fileid id="z0001_827">если б завтра да ненастье</fileid>
  <fileid id="z0001_828">чуть сердце у меня не выбили</fileid>
  <fileid id="z0001_829">или дернуть даже шестую сонату</fileid>
  <fileid id="z0001_830">когда проезжали лубянскую площадь ипполит матвеевич забеспокоился</fileid>
  <fileid id="z0001_831">жаль расстаться мне с бульваром</fileid>
  <fileid id="z0001_832">вдруг какой то безумец огонь с цепи спустил на волю и опять все гибнет</fileid>
  <fileid id="z0001_833">день не пропал даром и старый билль доволен собой</fileid>
  <fileid id="z0001_834">знаешь же сама какая езда</fileid>
  <fileid id="z0001_835">фотограф на всякий случай стал отбрехиваться</fileid>
  <fileid id="z0001_836">я ведь же тебя люблю ты такой бледненький</fileid>
  <fileid id="z0001_837">он жмет мне на прощанье руку</fileid>
  <fileid id="z0001_838">пусть бренчит себе на лире</fileid>
  <fileid id="z0001_839">очень даже обидно это от вас слышать</fileid>
  <fileid id="z0001_840">да ты их когда нибудь видела</fileid>
  <fileid id="z0001_841">но не думаете же вы лишить земной шар всей его атмосферы</fileid>
  <fileid id="z0001_842">и не забывайте надувать щеки</fileid>
  <fileid id="z0001_843">солнце грело в полную силу</fileid>
  <fileid id="z0001_844">и так мне в сердце ударило будто с камнем</fileid>
  <fileid id="z0001_845">ха ха зловеще захохотал химиков</fileid>
  <fileid id="z0001_846">вы видите они безопасны как дети</fileid>
  <fileid id="z0001_847">трубецкой был судьей тоже канцлера графа бестужева</fileid>
  <fileid id="z0001_848">угадавшему остап брался уплатить на месте</fileid>
  <fileid id="z0001_849">уж вы о нем мне не говорите</fileid>
  <fileid id="z0001_850">коровичий сын свою маму спать ведет</fileid>
  <fileid id="z0001_851">на их спор собрались любопытные</fileid>
  <fileid id="z0001_852">новая мысль озарила сережкину голову</fileid>
  <fileid id="z0001_853">эй ты там держись лучше</fileid>
  <fileid id="z0001_854">я слышал плач женщин и свист девочки</fileid>
  <fileid id="z0001_855">очень ли тебе больно спросил он</fileid>
  <fileid id="z0001_856">он уж лет тридцать будет как помер</fileid>
  <fileid id="z0001_857">созвучный эпохе хунтов принимался за повести</fileid>
  <fileid id="z0001_858">все таки это ведь заграница</fileid>
  <fileid id="z0001_859">ну еще парочку с зернистой</fileid>
  <fileid id="z0001_860">на это деньги надо голубчик</fileid>
  <fileid id="z0001_861">я тогда не хотел а теперь хочу</fileid>
  <fileid id="z0001_862">теперь дети не играют а учатся</fileid>
  <fileid id="z0001_863">три месяца живет на мой счет</fileid>
  <fileid id="z0001_864">теперь же скажи мне какая я</fileid>
  <fileid id="z0001_865">действие теплоты земного шара и солнца сказывалось даже сквозь все изоляционные преграждения</fileid>
  <fileid id="z0001_866">ты уж подожди на извозчике</fileid>
  <fileid id="z0001_867">ну будем считать через десять</fileid>
  <fileid id="z0001_868">зурита истощив весь запас ругательств вернулся на шхуну</fileid>
  <fileid id="z0001_869">на другой день печаль разрывала наши сердца нужно было уезжать</fileid>
  <fileid id="z0001_870">и сквозь слезы как солнце сквозь капли дождя проглянула счастливая улыбка</fileid>
  <fileid id="z0001_871">а я вчера очень заинтриговал елену сергеевну</fileid>
  <fileid id="z0001_872">да не более двух тысяч метров</fileid>
  <fileid id="z0001_873">конец письма даже рассмешил ее</fileid>
  <fileid id="z0001_874">и вдруг какая то мысль прорвалась и осветила его лицо</fileid>
  <fileid id="z0001_875">он сумел приручить дельфина ему известна обработка металлов</fileid>
  <fileid id="z0001_876">напрягая ослабевшие мышцы мы с профессором подняли камни</fileid>
  <fileid id="z0001_877">когда ассоль исполнилось восемь лет отец выучил ее читать и писать</fileid>
  <fileid id="z0001_878">воробьянинов запыхтел и покорно сказал</fileid>
  <fileid id="z0001_879">ты ведь писатель и имеешь право</fileid>
  <fileid id="z0001_880">они ведь привыкли к жаркому климату</fileid>
  <fileid id="z0001_881">остап моментально вернулся со ста рублями</fileid>
  <fileid id="z0001_882">ну еще что нибудь расскажите</fileid>
  <fileid id="z0001_883">я сам себя возвожу в гении</fileid>
  <fileid id="z0001_884">на палубе шхуны лежали полуголые ловцы жемчуга</fileid>
  <fileid id="z0001_885">никола был большой мастер резать по кости</fileid>
  <fileid id="z0001_886">индеец там есть стрелок и негр</fileid>
  <fileid id="z0001_887">короче говоря место за вами</fileid>
  <fileid id="z0001_888">и в финале всего сто пятьдесят тысяч рублей ноль ноль копеек</fileid>
  <fileid id="z0001_889">остап вызвал колю в коридор</fileid>
  <fileid id="z0001_890">это вы очень хорошо сказали</fileid>
  <fileid id="z0001_891">и двадцать молодых тезеев несли в париж шкуру минотавра</fileid>
  <fileid id="z0001_892">смотрим наконец ползет какой то дед в тулупе с клюкой</fileid>
  <fileid id="z0001_893">быть может отец норы корыстный человек</fileid>
  <fileid id="z0001_894">да для вас беда не большая</fileid>
  <fileid id="z0001_895">из тех что ты мне на расходы дашь</fileid>
  <fileid id="z0001_896">граф жил в батурине в огромном деревянном доме</fileid>
  <fileid id="z0001_897">выстрел был послан и он достиг цели</fileid>
  <fileid id="z0001_898">старые лубочные картины теперь очень редки</fileid>
  <fileid id="z0001_899">таковы уж все маленькие женщины</fileid>
  <fileid id="z0001_900">последнюю оглядывал царь беляеву из монастырок</fileid>
  <fileid id="z0001_901">за оставление своего поста граф был императрицею уволен</fileid>
  <fileid id="z0001_902">взять бы утюг хороший да разгладить</fileid>
  <fileid id="z0001_903">там наверное сидят уже из всех редакций</fileid>
  <fileid id="z0001_904">остап запрыгал по лестнице ведущей на пристань</fileid>
  <fileid id="z0001_905">остап задумчиво обошел кругом воробьянинова</fileid>
  <fileid id="z0001_906">за месяц было зарегистрировано более двух тысяч конкурсов</fileid>
  <fileid id="z0001_907">дворник погладил цементный бок колодца и пошел к мастерской</fileid>
  <fileid id="z0001_908">я же вам говорю что отец мерзавец</fileid>
  <fileid id="z0001_909">не такой это теперь продукт</fileid>
  <fileid id="z0001_910">ловкач художник просто изобразил внутренность нормандской хижины</fileid>
  <fileid id="z0001_911">но в этот момент я услышал за собою хрип</fileid>
  <fileid id="z0001_912">беременные женщины были очень недовольны</fileid>
  <fileid id="z0001_913">две дочери в гимназии учатся</fileid>
  <fileid id="z0001_914">что вы о ней скажете синьоры</fileid>
  <fileid id="z0001_915">митя отказался и теперь жестоко поплатился за это</fileid>
  <fileid id="z0001_916">под ней на таксометре красовалась цифра два лиры</fileid>
  <fileid id="z0001_917">не говорите мне о ней эльза</fileid>
  <fileid id="z0001_918">остап иронически посмотрел на ипполита матвеевича</fileid>
  <fileid id="z0001_919">и чем же кончился ваш разговор</fileid>
  <fileid id="z0001_920">где же он теперь этот ваш рыцарь без страха но с массой упреков</fileid>
  <fileid id="z0001_921">вы наверно прочли в газете</fileid>
  <fileid id="z0001_922">эрнест павлович чуть не заревел</fileid>
  <fileid id="z0001_923">весь день потом фигура отца федора мелькала во всех концах дачи</fileid>
  <fileid id="z0001_924">а вот товарищ говорил что вы знаете</fileid>
  <fileid id="z0001_925">утверждали что граф бежал от долгов</fileid>
  <fileid id="z0001_926">ты же сама еще и играешь графиню</fileid>
  <fileid id="z0001_927">она будет очень рада вас видеть</fileid>
  <fileid id="z0001_928">очень рада приветливо сказал суфлер</fileid>
  <fileid id="z0001_929">соседи даже в ложах фыркали от смеха</fileid>
  <fileid id="z0001_930">какие то семь паршивых ступенек</fileid>
  <fileid id="z0001_931">он бежал вдоль берега спотыкаясь гремя баночками и размахивая удочкой</fileid>
  <fileid id="z0001_932">и кроме того множество золотых и бриллиантовых вещей</fileid>
  <fileid id="z0001_933">из за спины дельфина показалась зеленая рука ударившая животное по спине</fileid>
  <fileid id="z0001_934">ужасы которые штирнер сеет вокруг себя</fileid>
  <fileid id="z0001_935">настоящую любовь ничто не убьет</fileid>
  <fileid id="z0001_936">да ведь заглавие то на обложке</fileid>
  <fileid id="z0001_937">я когда нибудь встречу ягуара</fileid>
  <fileid id="z0001_938">остап горделиво двинулся в путь</fileid>
  <fileid id="z0001_939">солнце тысячу раз отразилось в боевых доспехах</fileid>
  <fileid id="z0001_940">он опять ехидно подмигнул мне</fileid>
  <fileid id="z0001_941">но надо быть очень осторожным</fileid>
  <fileid id="z0001_942">это был очень опасный момент</fileid>
  <fileid id="z0001_943">милый людвиг у меня к тебе две просьбы</fileid>
  <fileid id="z0001_944">тихий плач переходит в рыдание</fileid>
  <fileid id="z0001_945">человек поразивший ее своей красотой был скульптор</fileid>
  <fileid id="z0001_946">остап без приглашения придвинул стул и сел</fileid>
  <fileid id="z0001_947">ипполит матвеевич сильно похудел и у него стала побаливать печень</fileid>
  <fileid id="z0001_948">одна ножка стола короче других</fileid>
  <fileid id="z0001_949">возьми толстой ты увидишь как это хорошо тотчас отобьет весь хмель</fileid>
  <fileid id="z0001_950">рыбаки же часто выручают из беды дельфинов</fileid>
  <fileid id="z0001_951">надо все обдумать и приготовить</fileid>
  <fileid id="z0001_952">я вижу что вы делаете успехи</fileid>
  <fileid id="z0001_953">уж поистине небу жарко станет</fileid>
  <fileid id="z0001_954">остап вернулся с новой микстурой</fileid>
  <fileid id="z0001_955">мне трудно оправдаться перед царем</fileid>
  <fileid id="z0001_956">на яхте развевался красный флаг</fileid>
  <fileid id="z0001_957">но теперь со всем этим кончено</fileid>
  <fileid id="z0001_958">вася придавал скульптуре последний лоск</fileid>
  <fileid id="z0001_959">дайте нам какого нибудь человека</fileid>
  <fileid id="z0001_960">принесите мне платок из ридикюля</fileid>
  <fileid id="z0001_961">а то смотри еще потеряешь меня</fileid>
  <fileid id="z0001_962">ты чего на нашей улице задавался</fileid>
  <fileid id="z0001_963">при отделении астрального тела от физического физическое тело должно спать</fileid>
  <fileid id="z0001_964">это довело его наконец до того что он стал считать мысленно</fileid>
  <fileid id="z0001_965">я женюсь сказал он любовнице</fileid>
  <fileid id="z0001_966">он ответил отец сидит там с пеной у рта</fileid>
  <fileid id="z0001_967">собираюсь лететь на новую землю</fileid>
  <fileid id="z0001_968">постепенно ускоряя ритм виртуоз достиг вершин балалаечной техники</fileid>
  <fileid id="z0001_969">тут вот с вас нужно штраф взыскать</fileid>
  <fileid id="z0001_970">улыбки заиграли на лицах фельдшера и акушерок</fileid>
  <fileid id="z0001_971">чтоб духом твоим у меня не пахло</fileid>
  <fileid id="z0001_972">несмотря на то что уже началась зима экспедиция выступила в путь</fileid>
  <fileid id="z0001_973">в поданной записке означены были лучшие волости и более трех тысяч душ</fileid>
  <fileid id="z0001_974">да уж лет двадцать к кровати стало тянуть</fileid>
  <fileid id="z0001_975">а здесь и своих гробовщиков хватит</fileid>
  <fileid id="z0001_976">я про сифилис а он про глотку</fileid>
  <fileid id="z0001_977">шульгин с горя стал придерживаться чарочки</fileid>
  <fileid id="z0001_978">плохо вот с бельем приходится</fileid>
  <fileid id="z0001_979">в лермонтовской галерее продавали нарзан</fileid>
  <fileid id="z0001_980">а через два дня младенец был мною забыт</fileid>
  <fileid id="z0001_981">и я закричал еще громче</fileid>
  <fileid id="z0001_982">ну что же теперь лучше себя чувствуете</fileid>
  <fileid id="z0001_983">первый стакан кьянти приободрил нас</fileid>
  <fileid id="z0001_984">вдова бежала по улице и голосила</fileid>
  <fileid id="z0001_985">но на другой день пушки вновь загремели</fileid>
  <fileid id="z0001_986">варфоломеич брал в залог вещи и назначал людоедские проценты</fileid>
  <fileid id="z0001_987">тем не менее остап велел ехать и искать</fileid>
  <fileid id="z0001_988">пришлось и эллочке обзавестись новой мебелью</fileid>
  <fileid id="z0001_989">но разве ваша философия менее циркульна</fileid>
  <fileid id="z0001_990">много ли нужно чтобы быть счастливым</fileid>
  <fileid id="z0001_991">лужи снова затянуло ломким вафельным льдом</fileid>
  <fileid id="z0001_992">хватающая за сердце пауза длилась целую минуту</fileid>
  <fileid id="z0001_993">и тут же показалось что то темное</fileid>
  <fileid id="z0001_994">у меня осталось шестьдесят рублей</fileid>
  <fileid id="z0001_995">очень не любил французов и был враг тогдашней французской философии</fileid>
  <fileid id="z0001_996">зачем вы оставили стул за дверью</fileid>
  <fileid id="z0001_997">остап глянул в звездное небо и вынул из кармана известные уже плоскогубцы</fileid>
  <fileid id="z0001_998">один из нас должен уехать из харькова</fileid>
  <fileid id="z0001_999">потом рудольф взял бритву и начал ею брить</fileid>
</recording_script>
